pisoundtrack/__init__.py
pisoundtrack/__main__.py
pisoundtrack/config-template.yml
pisoundtrack/soundtrack.py
pisoundtrack-0.2.5.dist-info/LICENSE
pisoundtrack-0.2.5.dist-info/METADATA
pisoundtrack-0.2.5.dist-info/WHEEL
pisoundtrack-0.2.5.dist-info/top_level.txt
pisoundtrack-0.2.5.dist-info/RECORD
